fooetalparam/__init__.py
fooetalparam/fooetalparam.py
fooetalparam-0.1.dist-info/METADATA
fooetalparam-0.1.dist-info/WHEEL
fooetalparam-0.1.dist-info/top_level.txt
fooetalparam-0.1.dist-info/RECORD
