Metadata-Version: 2.1
Name: fooetalparam
Version: 0.1
Home-page: https://github.com/bennyantony2500/fooetalparam
Download-URL: https://github.com/bennyantony2500/fooetalparam/archive/refs/tags/v_1.tar.gz
Author: Benny Antony
Author-email: bennyantony2500@gmail.com
License: MIT
Requires-Dist: pytest
Requires-Dist: argparse
